leakpy/__init__.py
leakpy/api.py
leakpy/cache.py
leakpy/cli.py
leakpy/config.py
leakpy/events.py
leakpy/leakix.py
leakpy/logger.py
leakpy/stats.py
leakpy/helpers/__init__.py
leakpy/helpers/batch.py
leakpy/helpers/bulk.py
leakpy/helpers/cache_utils.py
leakpy/helpers/cli_execution.py
leakpy/helpers/config_utils.py
leakpy/helpers/constants.py
leakpy/helpers/data_utils.py
leakpy/helpers/decorators.py
leakpy/helpers/display.py
leakpy/helpers/fetch.py
leakpy/helpers/field_utils.py
leakpy/helpers/file_operations.py
leakpy/helpers/l9event.py
leakpy/helpers/logging_utils.py
leakpy/helpers/lookup.py
leakpy/helpers/progress.py
leakpy/helpers/schema.py
leakpy/helpers/service_leak.py
leakpy-2.2.6.dist-info/licenses/LICENSE.rst
tests/__init__.py
tests/doc_examples_test.py
tests/examples_md_test.py
tests/readme_md_test.py
tests/run_tests.py
tests/test_cache_stats.py
tests/test_config.py
tests/test_domain.py
tests/test_host.py
tests/test_logger.py
tests/test_lookup_cli.py
tests/test_parser.py
tests/test_robustness.py
tests/test_subdomains.py
leakpy-2.2.6.dist-info/METADATA
leakpy-2.2.6.dist-info/WHEEL
leakpy-2.2.6.dist-info/entry_points.txt
leakpy-2.2.6.dist-info/top_level.txt
leakpy-2.2.6.dist-info/RECORD
