Metadata-Version: 2.4
Name: leakpy
Version: 2.2.6
Summary: LeakIX API Client
Home-page: https://github.com/Chocapikk/LeakPy
Author: Valentin Lobstein
Author-email: balgogan@protonmail.com
Project-URL: Bug Tracker, https://github.com/Chocapikk/LeakPy/issues
Project-URL: Documentation, https://leakpy.readthedocs.io/
Project-URL: Source Code, https://github.com/Chocapikk/LeakPy
Classifier: Programming Language :: Python :: 3
Classifier: Operating System :: OS Independent
Classifier: Development Status :: 5 - Production/Stable
Classifier: Intended Audience :: Developers
Classifier: Intended Audience :: Information Technology
Classifier: Topic :: Security
Classifier: Topic :: Internet :: Log Analysis
Requires-Python: >=3.9
License-File: LICENSE.rst
Requires-Dist: requests
Requires-Dist: rich
Requires-Dist: prompt_toolkit
Requires-Dist: keyring>=23.0.0
Requires-Dist: l9format>=1.3.2
Provides-Extra: docs
Requires-Dist: sphinx>=5.0.0; extra == "docs"
Requires-Dist: sphinx-rtd-theme>=1.0.0; extra == "docs"
Requires-Dist: myst-parser>=0.18.0; extra == "docs"
Dynamic: author
Dynamic: author-email
Dynamic: classifier
Dynamic: description
Dynamic: description-content-type
Dynamic: home-page
Dynamic: license-file
Dynamic: project-url
Dynamic: provides-extra
Dynamic: requires-dist
Dynamic: requires-python
Dynamic: summary
